setup.py
geomag_wdc_web_app_interface.egg-info/PKG-INFO
geomag_wdc_web_app_interface.egg-info/SOURCES.txt
geomag_wdc_web_app_interface.egg-info/dependency_links.txt
geomag_wdc_web_app_interface.egg-info/not-zip-safe
geomag_wdc_web_app_interface.egg-info/requires.txt
geomag_wdc_web_app_interface.egg-info/top_level.txt
lib/__init__.py
lib/consume_webservices.py
lib/sandboxed_format.py
tests/__init__.py
tests/datarequest_tests.py
tests/formdata_tests.py
tests/functional_tests.py
tests/parsed_config_file_tests.py