Metadata-Version: 1.2
Name: geomag-wdc-web-app-interface
Version: 1.0.5
Summary: Retrieve geomagnetic observatory data via WDC and INTERMAGNET web services
Home-page: https://github.com/willjbrown88/geomag_wdc_web_app_interface
Author: W. Brown
Author-email: wb@bgs.ac.uk
License: MIT
Download-URL: https://github.com/willjbrown88/geomag_wdc_web_app_interface/archive/1.0.5.tar.gz
Keywords: geomagnetism,geomagnetic observatory data,wdc,intermagnet
Platform: UNKNOWN
Requires-Python: >=3.4
